LICENSE
MANIFEST.in
README.md
pyproject.toml
requirements.txt
setup.py
helpers/__init__.py
kozmo_ai/__init__.py
kozmo_ai.egg-info/PKG-INFO
kozmo_ai.egg-info/SOURCES.txt
kozmo_ai.egg-info/dependency_links.txt
kozmo_ai.egg-info/entry_points.txt
kozmo_ai.egg-info/requires.txt
kozmo_ai.egg-info/top_level.txt
kozmo_ai/ai/__init__.py
kozmo_ai/ai/ai_client.py
kozmo_ai/ai/constants.py
kozmo_ai/ai/generator.py
kozmo_ai/ai/generator_cmds.py
kozmo_ai/ai/hugging_face_client.py
kozmo_ai/ai/llm_pipeline_wizard.py
kozmo_ai/ai/openai_client.py
kozmo_ai/ai/utils/__init__.py
kozmo_ai/ai/utils/xgboost.py
kozmo_ai/api/__init__.py
kozmo_ai/api/api_context.py
kozmo_ai/api/constants.py
kozmo_ai/api/errors.py
kozmo_ai/api/logging.py
kozmo_ai/api/middleware.py
kozmo_ai/api/oauth_scope.py
kozmo_ai/api/result_set.py
kozmo_ai/api/utils.py
kozmo_ai/api/views.py
kozmo_ai/api/mixins/__init__.py
kozmo_ai/api/mixins/result_set.py
kozmo_ai/api/monitors/BaseMonitor.py
kozmo_ai/api/monitors/__init__.py
kozmo_ai/api/operations/__init__.py
kozmo_ai/api/operations/base.py
kozmo_ai/api/operations/constants.py
kozmo_ai/api/parsers/BaseParser.py
kozmo_ai/api/parsers/PipelineScheduleParser.py
kozmo_ai/api/parsers/ProjectParser.py
kozmo_ai/api/parsers/RoleParser.py
kozmo_ai/api/parsers/UserParser.py
kozmo_ai/api/parsers/__init__.py
kozmo_ai/api/policies/AutocompleteItemPolicy.py
kozmo_ai/api/policies/BackfillPolicy.py
kozmo_ai/api/policies/BasePolicy.py
kozmo_ai/api/policies/BlockLayoutItemPolicy.py
kozmo_ai/api/policies/BlockOutputPolicy.py
kozmo_ai/api/policies/BlockPolicy.py
kozmo_ai/api/policies/BlockRunPolicy.py
kozmo_ai/api/policies/BlockTemplatePolicy.py
kozmo_ai/api/policies/CacheItemPolicy.py
kozmo_ai/api/policies/ClientPagePolicy.py
kozmo_ai/api/policies/ClusterPolicy.py
kozmo_ai/api/policies/CommandCenterItemPolicy.py
kozmo_ai/api/policies/ComputeClusterPolicy.py
kozmo_ai/api/policies/ComputeConnectionPolicy.py
kozmo_ai/api/policies/ComputeServicePolicy.py
kozmo_ai/api/policies/ConfigurationOptionPolicy.py
kozmo_ai/api/policies/CustomDesignPolicy.py
kozmo_ai/api/policies/CustomTemplatePolicy.py
kozmo_ai/api/policies/DataProviderPolicy.py
kozmo_ai/api/policies/DownloadPolicy.py
