Metadata-Version: 2.1
Name: kozmo-ai
Version: 0.1.3
Summary: Kozmo is a tool for building and deploying data pipelines.
Home-page: https://github.com/kozmoai/kozmoai
Author: Kozmoai
Author-email: contact@kozmoai.com
Classifier: Programming Language :: Python :: 3
Classifier: License :: OSI Approved :: Apache Software License
Classifier: Operating System :: OS Independent
Requires-Python: >=3.7
License-File: LICENSE
Requires-Dist: Faker==4.14.0
Requires-Dist: GitPython==3.1.41
Requires-Dist: Jinja2==3.1.3
Requires-Dist: Pillow==10.3.0
Requires-Dist: PyGithub==1.59.0
Requires-Dist: PyJWT==2.6.0
Requires-Dist: aiofiles==22.1.0
Requires-Dist: alembic>=1.7.5
Requires-Dist: bcrypt==4.0.1
Requires-Dist: croniter==1.3.7
Requires-Dist: cryptography==41.0.6
Requires-Dist: dask>=2022.2.0
Requires-Dist: datadog==0.44.0
Requires-Dist: freezegun==1.2.2
Requires-Dist: great-expectations==0.18.12
Requires-Dist: httpx==0.23.1
Requires-Dist: inflection==0.5.1
Requires-Dist: ipykernel==6.15.0
Requires-Dist: ipython==8.10.0
Requires-Dist: itsdangerous~=1.1.0
Requires-Dist: joblib>=1.1.0
Requires-Dist: jupyter-server-proxy==3.2.3
Requires-Dist: jupyter-server==1.23.5
Requires-Dist: jupyter_client==7.4.4
Requires-Dist: ldap3==2.9.1
Requires-Dist: newrelic==8.8.0
Requires-Dist: numpy>=1.22.0
Requires-Dist: pandas>=1.3.0
Requires-Dist: polars<0.19.2,>=0.18.0
Requires-Dist: protobuf~=4.21.12
Requires-Dist: pyarrow==14.0.1
Requires-Dist: python-dateutil==2.8.2
Requires-Dist: pytz>=2022.2.1
Requires-Dist: pyyaml~=6.0
Requires-Dist: redis~=5.0.1
Requires-Dist: requests~=2.31.0
Requires-Dist: ruamel.yaml==0.17.17
Requires-Dist: scikit-learn>=1.0
Requires-Dist: sentry-sdk==1.19.1
Requires-Dist: simplejson
Requires-Dist: six>=1.15.0
Requires-Dist: sqlalchemy<2.0.0,>=1.4.20
Requires-Dist: sqlglot[rs]
Requires-Dist: terminado==0.17.1
Requires-Dist: thefuzz[speedup]==0.19.0
Requires-Dist: tornado==6.3.3
Requires-Dist: typer[all]==0.9.0
Requires-Dist: typing_extensions==4.10.0
Requires-Dist: watchdog==4.0.0
Provides-Extra: ai
Requires-Dist: astor>=0.8.1; extra == "ai"
Requires-Dist: langchain>=0.0.222; extra == "ai"
Requires-Dist: langchain_community<0.0.20; extra == "ai"
Requires-Dist: openai<1.0.0,>=0.27.8; extra == "ai"
Provides-Extra: azure
Requires-Dist: azure-eventhub==5.11.2; extra == "azure"
Requires-Dist: azure-identity==1.12.0; extra == "azure"
Requires-Dist: azure-keyvault-secrets==4.6.0; extra == "azure"
Requires-Dist: azure-keyvault-certificates==4.6.0; extra == "azure"
Requires-Dist: azure-mgmt-containerinstance==10.1.0; extra == "azure"
Requires-Dist: azure-storage-blob==12.14.1; extra == "azure"
Provides-Extra: bigquery
Requires-Dist: google-cloud-bigquery~=3.0; extra == "bigquery"
Requires-Dist: db-dtypes==1.0.5; extra == "bigquery"
Provides-Extra: chroma
Requires-Dist: chromadb>=0.4.17; extra == "chroma"
Provides-Extra: clickhouse
Requires-Dist: clickhouse-connect~=0.6.23; extra == "clickhouse"
Provides-Extra: dbt
Requires-Dist: dbt-bigquery==1.7.2; extra == "dbt"
Requires-Dist: dbt-clickhouse==1.7.1; extra == "dbt"
Requires-Dist: dbt-core~=1.7.0; extra == "dbt"
Requires-Dist: dbt-duckdb~=1.7.0; extra == "dbt"
Requires-Dist: dbt-postgres~=1.7.4; extra == "dbt"
Requires-Dist: dbt-redshift~=1.7.1; extra == "dbt"
Requires-Dist: dbt-snowflake~=1.7.1; extra == "dbt"
Requires-Dist: dbt-spark~=1.7.1; extra == "dbt"
Requires-Dist: dbt-trino~=1.7.1; extra == "dbt"
Requires-Dist: trino~=0.326; extra == "dbt"
Provides-Extra: google-cloud-storage
Requires-Dist: google-cloud-storage==2.5.0; extra == "google-cloud-storage"
Requires-Dist: gspread==5.7.2; extra == "google-cloud-storage"
Provides-Extra: hdf5
Requires-Dist: tables==3.7.0; extra == "hdf5"
Provides-Extra: mysql
Requires-Dist: mysql-connector-python~=8.2.0; extra == "mysql"
Provides-Extra: oracle
Requires-Dist: oracledb==1.3.1; extra == "oracle"
Provides-Extra: postgres
Requires-Dist: psycopg2==2.9.3; extra == "postgres"
Requires-Dist: psycopg2-binary==2.9.3; extra == "postgres"
Requires-Dist: sshtunnel==0.4.0; extra == "postgres"
Provides-Extra: qdrant
Requires-Dist: qdrant-client==1.6.9; extra == "qdrant"
Requires-Dist: sentence-transformers==2.2.2; extra == "qdrant"
Provides-Extra: redshift
Requires-Dist: boto3==1.26.60; extra == "redshift"
Requires-Dist: redshift-connector==2.0.915; extra == "redshift"
Requires-Dist: lxml==4.9.4; extra == "redshift"
Provides-Extra: s3
Requires-Dist: boto3==1.26.60; extra == "s3"
Requires-Dist: botocore==1.29.60; extra == "s3"
Provides-Extra: snowflake
Requires-Dist: snowflake-connector-python==3.5.0; extra == "snowflake"
Provides-Extra: spark
Requires-Dist: boto3==1.26.60; extra == "spark"
Requires-Dist: botocore==1.29.60; extra == "spark"
Provides-Extra: streaming
Requires-Dist: confluent-avro~=1.8.0; extra == "streaming"
Requires-Dist: elasticsearch==8.9.0; extra == "streaming"
Requires-Dist: influxdb_client==1.36.1; extra == "streaming"
Requires-Dist: kafka-python==2.0.2; extra == "streaming"
Requires-Dist: nats-py==2.6.0; extra == "streaming"
Requires-Dist: nkeys~=0.1.0; extra == "streaming"
Requires-Dist: opensearch-py==2.0.0; extra == "streaming"
Requires-Dist: pika==1.3.1; extra == "streaming"
Requires-Dist: pymongo==4.3.3; extra == "streaming"
Requires-Dist: requests_aws4auth==1.1.2; extra == "streaming"
Requires-Dist: stomp.py==8.1.0; extra == "streaming"
Provides-Extra: all
Requires-Dist: PyGithub==1.59.0; extra == "all"
Requires-Dist: astor>=0.8.1; extra == "all"
Requires-Dist: aws-secretsmanager-caching==1.1.1.5; extra == "all"
Requires-Dist: azure-eventhub==5.11.2; extra == "all"
Requires-Dist: azure-identity==1.12.0; extra == "all"
Requires-Dist: azure-keyvault-certificates==4.6.0; extra == "all"
Requires-Dist: azure-keyvault-secrets==4.6.0; extra == "all"
Requires-Dist: azure-mgmt-containerinstance==10.1.0; extra == "all"
Requires-Dist: azure-storage-blob==12.14.1; extra == "all"
Requires-Dist: boto3==1.26.60; extra == "all"
Requires-Dist: botocore==1.29.60; extra == "all"
Requires-Dist: clickhouse-connect~=0.6.23; extra == "all"
Requires-Dist: confluent-avro~=1.8.0; extra == "all"
Requires-Dist: db-dtypes==1.0.5; extra == "all"
Requires-Dist: dbt-bigquery==1.7.2; extra == "all"
Requires-Dist: dbt-clickhouse==1.7.1; extra == "all"
Requires-Dist: dbt-core==1.7.4; extra == "all"
Requires-Dist: dbt-duckdb==1.7.0; extra == "all"
Requires-Dist: dbt-postgres==1.7.4; extra == "all"
Requires-Dist: dbt-redshift==1.7.1; extra == "all"
Requires-Dist: dbt-snowflake==1.7.1; extra == "all"
Requires-Dist: dbt-spark==1.7.1; extra == "all"
Requires-Dist: dbt-sqlserver; extra == "all"
Requires-Dist: dbt-trino==1.7.1; extra == "all"
Requires-Dist: duckdb==0.9.2; extra == "all"
Requires-Dist: elasticsearch==8.9.0; extra == "all"
Requires-Dist: google-api-core~=2.15.0; extra == "all"
Requires-Dist: google-api-python-client~=2.70.0; extra == "all"
Requires-Dist: google-cloud-bigquery~=3.14.1; extra == "all"
Requires-Dist: google-cloud-iam~=2.13.0; extra == "all"
Requires-Dist: google-cloud-pubsub~=2.19.0; extra == "all"
Requires-Dist: google-cloud-run~=0.10.1; extra == "all"
Requires-Dist: google-cloud-storage~=2.5.0; extra == "all"
Requires-Dist: great-expectations==0.18.12; extra == "all"
Requires-Dist: gspread==5.7.2; extra == "all"
Requires-Dist: influxdb_client==1.36.1; extra == "all"
Requires-Dist: kafka-python==2.0.2; extra == "all"
Requires-Dist: kubernetes>=28.1.0; extra == "all"
Requires-Dist: langchain==0.1.6; extra == "all"
Requires-Dist: langchain_community<0.0.20; extra == "all"
Requires-Dist: ldap3==2.9.1; extra == "all"
Requires-Dist: nats-py==2.6.0; extra == "all"
Requires-Dist: nkeys~=0.1.0; extra == "all"
Requires-Dist: openai<1.0.0,>=0.27.8; extra == "all"
Requires-Dist: opensearch-py==2.0.0; extra == "all"
Requires-Dist: opentelemetry-api==1.22.0; extra == "all"
Requires-Dist: opentelemetry-exporter-prometheus==0.43b0; extra == "all"
Requires-Dist: opentelemetry-instrumentation-tornado~=0.43b0; extra == "all"
Requires-Dist: opentelemetry-exporter-otlp~=1.22.0; extra == "all"
Requires-Dist: opentelemetry-instrumentation-sqlalchemy~=0.42b0; extra == "all"
Requires-Dist: oracledb==1.3.1; extra == "all"
Requires-Dist: pika==1.3.1; extra == "all"
Requires-Dist: pinotdb==5.1.0; extra == "all"
Requires-Dist: prometheus_client>=0.18.0; extra == "all"
Requires-Dist: protobuf~=4.21.12; extra == "all"
Requires-Dist: psycopg2-binary==2.9.3; extra == "all"
Requires-Dist: psycopg2==2.9.3; extra == "all"
Requires-Dist: pydruid==0.6.5; extra == "all"
Requires-Dist: pymongo==4.3.3; extra == "all"
Requires-Dist: pyodbc==4.0.35; extra == "all"
Requires-Dist: redshift-connector==2.0.915; extra == "all"
Requires-Dist: lxml==4.9.4; extra == "all"
Requires-Dist: requests_aws4auth==1.1.2; extra == "all"
Requires-Dist: snowflake-connector-python==3.5.0; extra == "all"
Requires-Dist: sshtunnel==0.4.0; extra == "all"
Requires-Dist: stomp.py==8.1.0; extra == "all"
Requires-Dist: thefuzz[speedup]==0.19.0; extra == "all"
Requires-Dist: trino~=0.326; extra == "all"
